README.rst
setup.py
src/archive_api_client.egg-info/PKG-INFO
src/archive_api_client.egg-info/SOURCES.txt
src/archive_api_client.egg-info/dependency_links.txt
src/archive_api_client.egg-info/requires.txt
src/archive_api_client.egg-info/top_level.txt
src/archive_client/__init__.py
src/archive_client/client.py
src/archive_client/models.py
src/archive_client/session.py