Metadata-Version: 2.1
Name: archive-api-client
Version: 0.0.1
Summary: Python wrapper for the CNX Archive API(http://archive.cnx.org)
Home-page: UNKNOWN
Author: m1yag1
Author-email: mike.arbelaez@rice.edu
License: AGPLv3
Platform: UNKNOWN
